fairchem/core/LICENSE.md
fairchem/core/README.md
fairchem/core/__init__.py
fairchem/core/_cli.py
fairchem/core/_config.py
fairchem/core/calculate/__init__.py
fairchem/core/calculate/_batch.py
fairchem/core/calculate/ase_calculator.py
fairchem/core/calculate/pretrained_mlip.py
fairchem/core/calculate/pretrained_models.json
fairchem/core/common/__init__.py
fairchem/core/common/data_parallel.py
fairchem/core/common/distutils.py
fairchem/core/common/gp_utils.py
fairchem/core/common/logger.py
fairchem/core/common/profiler_utils.py
fairchem/core/common/registry.py
fairchem/core/common/test_utils.py
fairchem/core/common/typing.py
fairchem/core/common/utils.py
fairchem/core/components/reducer.py
fairchem/core/components/runner.py
fairchem/core/components/utils.py
fairchem/core/components/benchmark/__init__.py
fairchem/core/components/benchmark/_benchmark_reducer.py
fairchem/core/components/benchmark/_single/__init__.py
fairchem/core/components/benchmark/_single/adsorbml_reducer.py
fairchem/core/components/benchmark/_single/adsorption_reducer.py
fairchem/core/components/benchmark/_single/kappa_reducer.py
fairchem/core/components/benchmark/_single/materials_discovery_reducer.py
fairchem/core/components/benchmark/_single/nvemd_reducer.py
fairchem/core/components/benchmark/_single/omc_polymorph_reducer.py
fairchem/core/components/benchmark/_single/omol_reducer.py
fairchem/core/components/benchmark/_single/uma_speed_benchmark.py
fairchem/core/components/calculate/__init__.py
fairchem/core/components/calculate/_calculate_runner.py
fairchem/core/components/calculate/_single/__init__.py
fairchem/core/components/calculate/_single/adsorbml_runner.py
fairchem/core/components/calculate/_single/adsorption_runner.py
fairchem/core/components/calculate/_single/adsorption_singlepoint_runner.py
fairchem/core/components/calculate/_single/elasticity_runner.py
fairchem/core/components/calculate/_single/kappa_runner.py
fairchem/core/components/calculate/_single/nve_md_runner.py
fairchem_core-2.13.0.dist-info/METADATA
fairchem_core-2.13.0.dist-info/WHEEL
fairchem_core-2.13.0.dist-info/entry_points.txt
fairchem_core-2.13.0.dist-info/RECORD
