Metadata-Version: 2.4
Name: fairchem-core
Version: 2.13.0
Summary: Machine learning models for chemistry and materials science by the FAIR Chemistry team
Project-URL: repository, https://github.com/facebookresearch/fairchem
Project-URL: home, https://opencatalystproject.org/
Project-URL: documentation, https://fair-chem.github.io/
License: MIT License
Requires-Python: <3.14,>=3.10
Requires-Dist: ase-db-backends>=0.10.0
Requires-Dist: ase>=3.26.0
Requires-Dist: clusterscope==0.0.18
Requires-Dist: e3nn>=0.5
Requires-Dist: huggingface-hub>=0.27.1
Requires-Dist: hydra-core
Requires-Dist: lmdb<=1.7.3,>=1.6.2
Requires-Dist: monty>=v2025.1.3
Requires-Dist: numba>=0.62.0
Requires-Dist: numpy<2.4,>=2.0
Requires-Dist: orjson
Requires-Dist: pyyaml
Requires-Dist: ray[serve]>=2.50.0
Requires-Dist: requests
Requires-Dist: submitit
Requires-Dist: torchtnt
Requires-Dist: torch~=2.8.0
Requires-Dist: tqdm
Requires-Dist: wandb
Requires-Dist: websockets
Provides-Extra: adsorbml
Requires-Dist: dscribe; extra == 'adsorbml'
Requires-Dist: scikit-image; extra == 'adsorbml'
Requires-Dist: x3dase; extra == 'adsorbml'
Provides-Extra: dev
Requires-Dist: coverage; extra == 'dev'
Requires-Dist: pre-commit; extra == 'dev'
Requires-Dist: pytest; extra == 'dev'
Requires-Dist: pytest-cov; extra == 'dev'
Requires-Dist: ruff==0.5.1; extra == 'dev'
Requires-Dist: syrupy; extra == 'dev'
Provides-Extra: docs
Requires-Dist: astroid<4; extra == 'docs'
Requires-Dist: ipywidgets; extra == 'docs'
Requires-Dist: jupyter-book; extra == 'docs'
Requires-Dist: jupyter-book==1.0.4; extra == 'docs'
Requires-Dist: jupytext; extra == 'docs'
Requires-Dist: sphinx; extra == 'docs'
Requires-Dist: sphinx-autoapi==3.3.3; extra == 'docs'
Requires-Dist: sphinxcontrib-mermaid; extra == 'docs'
Requires-Dist: torch-dftd; extra == 'docs'
Requires-Dist: umap-learn; extra == 'docs'
Requires-Dist: vdict; extra == 'docs'
Provides-Extra: extras
Requires-Dist: pandas; extra == 'extras'
Requires-Dist: pymatgen; extra == 'extras'
Requires-Dist: quacc[phonons]>=0.15.3; extra == 'extras'
